[
  {
    "id": "34568",
    "customer": "Michael Johnson",
    "total": "$245.99",
    "payment": "Credit Card",
    "rider": "Unassigned",
    "status": "Pending"
  },
  {
    "id": "34568",
    "customer": "Sarah Williams",
    "total": "$189.50",
    "payment": "PayPal",
    "rider": "James Smith",
    "status": "In Transit"
  },
  {
    "id": "38886",
    "customer": "Robert Chen",
    "total": "$320.75",
    "payment": "Cash on Delivery",
    "rider": "Maria Garcia",
    "status": "Delivered"
  },
  {
    "id": "02586",
    "customer": "Emily Davis",
    "total": "$150.20",
    "payment": "Credit Card",
    "rider": "Unassigned",
    "status": "Pending"
  }
]
